honeypot/__init__.py
honeypot/client.py
honeypot/crypto.py
honeypot_server_api/__init__.py
honeypot_server_api/crypto.py
tests/__init__.py
tests/test_crypto.py
honeypot_py-0.2.18.dist-info/METADATA
honeypot_py-0.2.18.dist-info/WHEEL
honeypot_py-0.2.18.dist-info/top_level.txt
honeypot_py-0.2.18.dist-info/RECORD
